_pmcx.cpython-311-x86_64-linux-gnu.so
pmcx/__init__.py
pmcx/bench.py
pmcx/io.py
pmcx/plot.py
pmcx/utils.py
pmcx.libs/libgomp-a34b3233.so.1.0.0
pmcx-0.6.1.dist-info/METADATA
pmcx-0.6.1.dist-info/WHEEL
pmcx-0.6.1.dist-info/top_level.txt
pmcx-0.6.1.dist-info/RECORD
