Metadata-Version: 2.4
Name: pmcx
Version: 0.6.1
Summary: Python bindings for Monte Carlo eXtreme photon transport simulator
Home-page: https://github.com/fangq/mcx
Download-URL: https://mcx.space
Author: Matin Raayai Ardakani, Qianqian Fang, Fan-Yu Yen
Author-email: raayaiardakani.m@northeastern.edu, q.fang@neu.edu, yen.f@northeastern.edu
Maintainer: Qianqian Fang
License: GPLv3+
Keywords: Monte Carlo simulation,Biophotonics,Ray-tracing,Rendering,GPU,Modeling,Biomedical Optics,Tissue Optics,Simulator,Optics,NVIDIA,CUDA
Classifier: Development Status :: 4 - Beta
Classifier: Intended Audience :: Science/Research
Classifier: Environment :: GPU :: NVIDIA CUDA
Classifier: Topic :: Scientific/Engineering :: Physics
Classifier: Programming Language :: Python :: 3.6
Classifier: Programming Language :: Python :: 3.7
Classifier: Programming Language :: Python :: 3.8
Classifier: Programming Language :: Python :: 3.9
Classifier: Programming Language :: Python :: 3.10
Classifier: Programming Language :: Python :: 3.11
Classifier: Programming Language :: Python :: 3.12
Classifier: Programming Language :: Python :: 3.13
Requires: numpy
Requires-Python: >=3.6
Dynamic: author
Dynamic: author-email
Dynamic: classifier
Dynamic: description
Dynamic: description-content-type
Dynamic: download-url
Dynamic: home-page
Dynamic: keywords
Dynamic: license
Dynamic: maintainer
Dynamic: requires
Dynamic: requires-python
Dynamic: summary
